[{"StageID":1,"IsClear":1},{"StageID":2,"IsClear":0},{"StageID":3,"IsClear":0},{"StageID":4,"IsClear":0},{"StageID":5,"IsClear":0},{"StageID":6,"IsClear":0},{"StageID":7,"IsClear":0},{"StageID":8,"IsClear":0},{"StageID":9,"IsClear":0},{"StageID":10,"IsClear":0},{"StageID":11,"IsClear":0},{"StageID":12,"IsClear":0},{"StageID":13,"IsClear":0},{"StageID":14,"IsClear":0},{"StageID":15,"IsClear":0},{"StageID":16,"IsClear":0},{"StageID":17,"IsClear":0},{"StageID":18,"IsClear":0},{"StageID":19,"IsClear":0},{"StageID":20,"IsClear":0},{"StageID":21,"IsClear":0},{"StageID":22,"IsClear":0},{"StageID":23,"IsClear":0},{"StageID":24,"IsClear":0},{"StageID":25,"IsClear":0}]